{
    "lists": [
        {
            "name": "Mots fléchés",
            "flashcards": [
                {
                    "name": "Symbole étain (2)",
                    "definition": "Sn"
                },
                {
                    "name": "Petit ruisseau (2)",
                    "definition": "Ru"
                },
                {
                    "name": "Ancien Do (2)",
                    "definition": "Ut"
                },
                {
                    "name": "Bison disparu (3)",
                    "definition": "Ure"
                },
                {
                    "name": "Répéter trois fois en musique (3)",
                    "definition": "Ter"
                },
                {
                    "name": "Jeunes formés à l'opéra (4)",
                    "definition": "Rats"
                },
                {
                    "name": "Dépôt fond de bouteille (3)",
                    "definition": "Lie"
                },
                {
                    "name": "Céréale germée (4)",
                    "definition": "Malt"
                },
                {
                    "name": "Payé sans être dû (4)",
                    "definition": "Indu"
                },
                {
                    "name": "Croc du boucher (4)",
                    "definition": "Esse"
                },
                {
                    "name": "Branche pour greffe (4)",
                    "definition": "Ente"
                },
                {
                    "name": "Épée longue et fine (5)",
                    "definition": "Estoc"
                },
                {
                    "name": "Utiliser de manière régulière (6)",
                    "definition": "Usiter"
                },
                {
                    "name": "Gâteau chocolat (5)",
                    "definition": "Opera"
                },
                {
                    "name": "Crier pour un cerf (6/4)",
                    "definition": "Bramer / Réer"
                },
                {
                    "name": "Couper la cime (6)",
                    "definition": "Écimer"
                },
                {
                    "name": "Décapiter (6)",
                    "definition": "Étêter"
                },
                {
                    "name": "Être le premier à employer (8)",
                    "definition": "Étrenner"
                },
                {
                    "name": "Roche de talc (8)",
                    "definition": "Stéatite"
                },
                {
                    "name": "Veste de laine boutonnée (8)",
                    "definition": "Cardigan"
                },
                {
                    "name": "Siège de l'accusé (8)",
                    "definition": "Sellette"
                },
                {
                    "name": "Aiguiser un objet (8)",
                    "definition": "Émouler"
                },
                {
                    "name": "Estampe populaire (avec une ville)",
                    "definition": "Image d'Épinal"
                },
                {
                    "name": "Baie au Japon (3)",
                    "definition": "Ise"
                },
                {
                    "name": "Fleuve à Perpignan (3)",
                    "definition": "Têt"
                },
                {
                    "name": "Ville naissance Brassens (4)",
                    "definition": "Sète (trouver personne)"
                },
                {
                    "name": "Fleuve de Toscane (4)",
                    "definition": "Arno"
                },
                {
                    "name": "Port mer Rouge Israël (5)",
                    "definition": "Eilat"
                },
                {
                    "name": "Poète Grèce Antique (4)",
                    "definition": "Aède"
                },
                {
                    "name": "Élan d'oiseau qui s'envole (5)",
                    "definition": "Essor"
                },
                {
                    "name": "Désert rocheux (3)",
                    "definition": "Reg"
                },
                {
                    "name": "Pas blanchi/traité (4)",
                    "definition": "Écru"
                },
                {
                    "name": "Département Angoulême ",
                    "definition": "Ville Charente"
                },
                {
                    "name": "Département Sète",
                    "definition": "Ville Hérault"
                },
                {
                    "name": "Chipoter (7)",
                    "definition": "Ergoter"
                },
                {
                    "name": "Qui remplace (6)",
                    "definition": "Ersatz"
                },
                {
                    "name": "Petite galère (7)",
                    "definition": "Galiote"
                },
                {
                    "name": "Style de vie avec privation (6)",
                    "definition": "Ascèse"
                },
                {
                    "name": "Ruban étroit (6)",
                    "definition": "Liseré"
                },
                {
                    "name": "Versant face au soleil (5)",
                    "definition": "Adret"
                },
                {
                    "name": "Mécanisme de roue hydraulique pour remonter l'eau (5)",
                    "definition": "Noria"
                },
                {
                    "name": "De haute écosse (4)",
                    "definition": "Erse"
                },
                {
                    "name": "Délai accordé (12)",
                    "definition": "Atermoiement"
                },
                {
                    "name": "Calibrer une pièce (6)",
                    "definition": "Aleser"
                },
                {
                    "name": "Cité en Jordanie (5)",
                    "definition": "Pétra"
                },
                {
                    "name": "Île Britannique (3)",
                    "definition": "Man"
                },
                {
                    "name": "Partie immergée de la coque (6)",
                    "definition": "Carène"
                },
                {
                    "name": "Robe indienne (4)",
                    "definition": "Sari"
                },
                {
                    "name": "Enduit de ski (4)",
                    "definition": "Fart"
                },
                {
                    "name": "Course cycliste sur piste (6)",
                    "definition": "Omnium"
                },
                {
                    "name": "Petite cuve (6)",
                    "definition": "Cuveau"
                },
                {
                    "name": "Mystère (6)",
                    "definition": "Arcane"
                },
                {
                    "name": "Nicolas II (4)",
                    "definition": "Tsar"
                },
                {
                    "name": "Unité de mesure chinoise 500m (2)",
                    "definition": "Li"
                },
                {
                    "name": "Retour de vague (6)",
                    "definition": "Ressac"
                },
                {
                    "name": "Compact (3)",
                    "definition": "Dru"
                },
                {
                    "name": "Pantoufle (4)",
                    "definition": "Mule"
                },
                {
                    "name": "Oui en occitan (2)",
                    "definition": "Oc"
                },
                {
                    "name": "Département Troyes ",
                    "definition": "Ville Aube"
                },
                {
                    "name": "Chef imprimeur (5)",
                    "definition": "Prote"
                },
                {
                    "name": "Poignard malais (5)",
                    "definition": "Criss"
                },
                {
                    "name": "Type de vin italien (4)",
                    "definition": "Asti"
                },
                {
                    "name": "Style de théâtre japonais (2)",
                    "definition": "Nõ"
                },
                {
                    "name": "Arabe (4)",
                    "definition": "Maure"
                },
                {
                    "name": "Règle plate (2)",
                    "definition": "Té"
                },
                {
                    "name": "Centime de yen (3)",
                    "definition": "Sen"
                },
                {
                    "name": "Situé (3)",
                    "definition": "Sis"
                },
                {
                    "name": "Produit par l'hevéa (5)",
                    "definition": "Latex (produit par ?)"
                },
                {
                    "name": "Perroquet d'Asie (4)",
                    "definition": "Lori"
                },
                {
                    "name": "Symbole platine (2)",
                    "definition": "Pt"
                },
                {
                    "name": "Classification des groupes sanguins",
                    "definition": "Système Rhésus (Rh)"
                },
                {
                    "name": "Fleuve à Turin (2)",
                    "definition": "Po"
                },
                {
                    "name": "Garnir un voilier (5)",
                    "definition": "Gréer"
                },
                {
                    "name": "Prendre l'initiative d'un procès (5)",
                    "definition": "Ester"
                },
                {
                    "name": "Lettre en vers (6)",
                    "definition": "Epitre"
                },
                {
                    "name": "Literie japonaise (5)",
                    "definition": "Futon"
                },
                {
                    "name": "Ensemble de vers (6)",
                    "definition": "Stance"
                },
                {
                    "name": "Jamais (3)",
                    "definition": "Onc"
                },
                {
                    "name": "Oiseau arctique (11)",
                    "definition": "Stercoraire"
                },
                {
                    "name": "Déesse mère grecque (4 / 2)",
                    "definition": "Gaia / Ge"
                },
                {
                    "name": "Morte (4)",
                    "definition": "Feue"
                },
                {
                    "name": "Colère (3)",
                    "definition": "Ire"
                },
                {
                    "name": "Saut danse classique (9)",
                    "definition": "Entrechat"
                },
                {
                    "name": "Héro Troyen ",
                    "definition": "Énée"
                },
                {
                    "name": "Région d'Italie (7)",
                    "definition": "Piémont"
                },
                {
                    "name": "Roue (3)",
                    "definition": "Réa"
                },
                {
                    "name": "Panthère des neiges (4)",
                    "definition": "Once"
                },
                {
                    "name": "Part qui revient à chacun (9)",
                    "definition": "Quotepart"
                },
                {
                    "name": "Jeune couturière (8)",
                    "definition": "Cousette"
                },
                {
                    "name": "Trace de pneu (7)",
                    "definition": "Ornière"
                },
                {
                    "name": "Convenir (5)",
                    "definition": "Seoir"
                },
                {
                    "name": "Manque de fer (6)",
                    "definition": "Anémie"
                },
                {
                    "name": "100 m2 (3)",
                    "definition": "Are"
                },
                {
                    "name": "Langue Togo (3)",
                    "definition": "Éwé"
                },
                {
                    "name": "Pièce de bois mâle (5)",
                    "definition": "Tenon"
                },
                {
                    "name": "Se rapporte à la montagne (8)",
                    "definition": "Alpestre"
                },
                {
                    "name": "Tonus (3)",
                    "definition": "Pep"
                },
                {
                    "name": "Couronne papale (5)",
                    "definition": "Tiare"
                },
                {
                    "name": "Pièce de bois qui écarte (4)",
                    "definition": "Épar(t)"
                },
                {
                    "name": "Monnaie Bulgare (3)",
                    "definition": "Lev"
                },
                {
                    "name": "Préfixe nouveauté (3)",
                    "definition": "Néo"
                },
                {
                    "name": "Voile avant (3)",
                    "definition": "Foc"
                },
                {
                    "name": "Fleuve normand (4)",
                    "definition": "Orne"
                },
                {
                    "name": "Guerrier brutal (6)",
                    "definition": "Reitre"
                },
                {
                    "name": "Niveler (7)",
                    "definition": "Écrêter"
                },
                {
                    "name": "Il nie la Trinité (5)",
                    "definition": "Arien"
                },
                {
                    "name": "Poisson plie (8)",
                    "definition": "-Carrelet"
                },
                {
                    "name": "Plaider en faveur (10)",
                    "definition": "Intercéder"
                },
                {
                    "name": "Troisième note (2)",
                    "definition": "Mi"
                },
                {
                    "name": "Petite butte (6)",
                    "definition": "Tertre"
                },
                {
                    "name": "Rognon (4)",
                    "definition": "Rein"
                },
                {
                    "name": "Chanson populaire allemande (4)",
                    "definition": "Lied"
                },
                {
                    "name": "Haricot germé (4)",
                    "definition": "Soja (vert)"
                },
                {
                    "name": "Élégance (8)",
                    "definition": "Joliesse"
                },
                {
                    "name": "7ème lettre grecque (3)",
                    "definition": "Êta"
                },
                {
                    "name": "Dramaturge Grec (8)",
                    "definition": "Sophocle"
                },
                {
                    "name": "Personne naïve (6)",
                    "definition": "Gobeur"
                },
                {
                    "name": "Ancien sigle postal (3)",
                    "definition": "PTT"
                },
                {
                    "name": "Déesse des métiers (7)",
                    "definition": "Minerve"
                },
                {
                    "name": "1 en allemand (4)",
                    "definition": "Eins"
                },
                {
                    "name": "Douleur pied marcheur (3)",
                    "definition": "Cor"
                },
                {
                    "name": "L'orient (le) (6)",
                    "definition": "Levant"
                },
                {
                    "name": "Chapeau (6)",
                    "definition": "Panama"
                },
                {
                    "name": "Norme 4G (3)",
                    "definition": "LTE"
                },
                {
                    "name": "Ville Nigéria (3)",
                    "definition": "Ila (ville)"
                },
                {
                    "name": "Soldat de la jungle (10)",
                    "definition": "Guerillero"
                },
                {
                    "name": "Être grand ouvert (4)",
                    "definition": "Béer"
                },
                {
                    "name": "Fleuve nord France (2)",
                    "definition": "Aa"
                },
                {
                    "name": "Premier morceau coupé (6)",
                    "definition": "Entame"
                },
                {
                    "name": "Ulcération de la peau (7)",
                    "definition": "Chancre"
                },
                {
                    "name": "+ long que large (6)",
                    "definition": "Oblong"
                },
                {
                    "name": "Basilique Marseille",
                    "definition": "Bonne mère"
                },
                {
                    "name": "Collier prison (6)",
                    "definition": "Carcan"
                },
                {
                    "name": "Galère de combat antique (6)",
                    "definition": "Trière"
                },
                {
                    "name": "Pied (6)",
                    "definition": "Arpion"
                },
                {
                    "name": "Qui met la vie en danger (8)",
                    "definition": "Délétère"
                },
                {
                    "name": "Service parfait (3)",
                    "definition": "Ace"
                },
                {
                    "name": "Liste des faute (6)",
                    "definition": "Errata"
                },
                {
                    "name": "Brosse bijoutier (4)",
                    "definition": "Saie"
                },
                {
                    "name": "Plante nuisible céréales (6)",
                    "definition": "Ivraie"
                },
                {
                    "name": "Contraire au bon sens (6)",
                    "definition": "Insane"
                },
                {
                    "name": "Quantité négligeable (4)",
                    "definition": "Iota"
                },
                {
                    "name": "Respirer bruyamment (6)",
                    "definition": "Ahaner"
                },
                {
                    "name": "Population Zambie (3)",
                    "definition": "Ila (population)"
                },
                {
                    "name": "Bière anglaise haute fermentation (3)",
                    "definition": "Ale"
                },
                {
                    "name": "Agit pour le bien des siens (11)",
                    "definition": "Philanthrope"
                },
                {
                    "name": "Département Auch",
                    "definition": "Ville Gers"
                },
                {
                    "name": "Chefs armé (2)",
                    "definition": "EM"
                },
                {
                    "name": "Ville ouest Allemagne (5)",
                    "definition": "Essen"
                },
                {
                    "name": "Type laine mouton (7)",
                    "definition": "Mérinos"
                },
                {
                    "name": "Misérable (4)",
                    "definition": "Hère"
                },
                {
                    "name": "Maître de rhétorique (7)",
                    "definition": "Rheteur"
                },
                {
                    "name": "Petite vallée fluviale (3)",
                    "definition": "Ria"
                },
                {
                    "name": "Opéra solo (4)",
                    "definition": "Aria"
                },
                {
                    "name": "Résumé d'un livre (6)",
                    "definition": "Digest"
                },
                {
                    "name": "Orateur grec (4)",
                    "definition": "Isée"
                },
                {
                    "name": "Fards pour cil (6)",
                    "definition": "Rimmel"
                },
                {
                    "name": "Petite cerise (7)",
                    "definition": "Griotte"
                },
                {
                    "name": "Rouge vif (6)",
                    "definition": "Carmin"
                },
                {
                    "name": "Araignée du jardin (6)",
                    "definition": "Épeire"
                },
                {
                    "name": "Département Pau",
                    "definition": "Ville Béarn"
                },
                {
                    "name": "Résine puante (3)",
                    "definition": "Ase"
                },
                {
                    "name": "Petite maison bois russe (4)",
                    "definition": "Isba"
                },
                {
                    "name": "Poudre d'écorce (3)",
                    "definition": "Tan"
                },
                {
                    "name": "Central nucléaire nord France (10)",
                    "definition": "Gravelines"
                },
                {
                    "name": "Ancêtre de l'UE (3)",
                    "definition": "CEE"
                },
                {
                    "name": "Ancienne monnaie italienne (4)",
                    "definition": "Lire"
                },
                {
                    "name": "Affluent Dordogne (4)",
                    "definition": "Cère"
                },
                {
                    "name": "Note après Si",
                    "definition": "Note avant Do"
                },
                {
                    "name": "Matrice (6)",
                    "definition": "Utérus"
                },
                {
                    "name": "Type laine lapin (6)",
                    "definition": "Angora"
                },
                {
                    "name": "Berceau de fleuve (3)",
                    "definition": "Val"
                },
                {
                    "name": "Rejeter quelqu'un d'un groupe (10)",
                    "definition": "Ostraciser"
                },
                {
                    "name": "Balai rond",
                    "definition": "Tête de loup"
                },
                {
                    "name": "Invite à répéter (3)",
                    "definition": "Bis"
                },
                {
                    "name": "Fenêtre de toit (8)",
                    "definition": "Vasistas"
                },
                {
                    "name": "Cale en forme de V (2)",
                    "definition": "Vé"
                },
                {
                    "name": "Boisson grec anis (4)",
                    "definition": "Ouzo"
                },
                {
                    "name": "Signe début partition",
                    "definition": "Clé de portée"
                },
                {
                    "name": "Comité d'usine (2)",
                    "definition": "CE"
                },
                {
                    "name": "À la mode (2)",
                    "definition": "In"
                },
                {
                    "name": "Pied déformé (3)",
                    "definition": "Bot"
                },
                {
                    "name": "Voiture hippique (5)",
                    "definition": "Sulky"
                },
                {
                    "name": "Enveloppe noix (5)",
                    "definition": "Écale"
                },
                {
                    "name": "Nuage troposphère (6)",
                    "definition": "Cirrus"
                },
                {
                    "name": "Petit fagot(6)",
                    "definition": "Cotret"
                },
                {
                    "name": "Bride de cheval (5)",
                    "definition": "Rênes"
                },
                {
                    "name": "Trois As (5)",
                    "definition": "Brelan"
                },
                {
                    "name": "Ancien service féodal (3)",
                    "definition": "Ost"
                },
                {
                    "name": "Dieu Egypte Antique (2/2)",
                    "definition": "Ra/Ré"
                },
                {
                    "name": "Acide désagréable (5)",
                    "definition": "Aigre"
                },
                {
                    "name": "Bordure de forêt (4)",
                    "definition": "Orée"
                },
                {
                    "name": "Sautoir (6)",
                    "definition": "Collier"
                },
                {
                    "name": "Cavalière (4)",
                    "definition": "Osée"
                },
                {
                    "name": "Couvre de coups (5)",
                    "definition": "Rosse"
                },
                {
                    "name": "Petit chemin (5)",
                    "definition": "Sente"
                },
                {
                    "name": "Renonce à la religion (7)",
                    "definition": "Apostat"
                },
                {
                    "name": "Principe désir (4)",
                    "definition": "Éros"
                },
                {
                    "name": "Produit dopant (3)",
                    "definition": "EPO"
                },
                {
                    "name": "Premier département (3)",
                    "definition": "Ain"
                }
            ]
        },
        {
            "name": "Anglais",
            "flashcards": [
                {
                    "name": "Scullery",
                    "definition": "Arrière-cuisine"
                },
                {
                    "name": "Grate",
                    "definition": "Grille"
                },
                {
                    "name": "Slab",
                    "definition": "Dalle"
                },
                {
                    "name": "Dripping",
                    "definition": "Graisse"
                },
                {
                    "name": "Waistcoat",
                    "definition": "Gilet"
                },
                {
                    "name": "Stiff",
                    "definition": "Raide"
                },
                {
                    "name": "Stern",
                    "definition": "Sombre"
                },
                {
                    "name": "Rag",
                    "definition": "Chiffon"
                },
                {
                    "name": "Scornful",
                    "definition": "Méprisant"
                },
                {
                    "name": "Boned",
                    "definition": "Désossé"
                },
                {
                    "name": "Bodice",
                    "definition": "Corsage"
                },
                {
                    "name": "Hooped",
                    "definition": "Cerclé"
                },
                {
                    "name": "Cognoscenti",
                    "definition": "Connaisseurs"
                },
                {
                    "name": "Frock",
                    "definition": "Robe"
                },
                {
                    "name": "Glossy",
                    "definition": "Brillant"
                },
                {
                    "name": "Lace",
                    "definition": "Dentelle"
                },
                {
                    "name": "Corrugated",
                    "definition": "Ondulé"
                },
                {
                    "name": "Mahogany",
                    "definition": "Acajou"
                },
                {
                    "name": "Twinkled",
                    "definition": "Scintillé"
                },
                {
                    "name": "Vicar",
                    "definition": "Curé"
                },
                {
                    "name": "Snap",
                    "definition": "Claquement"
                },
                {
                    "name": "Tin",
                    "definition": "Étain"
                },
                {
                    "name": "Mantelpiece",
                    "definition": "Cheminée"
                },
                {
                    "name": "Leaped",
                    "definition": "Sauté"
                },
                {
                    "name": "Trouser",
                    "definition": "Pantalon"
                },
                {
                    "name": "Wippy",
                    "definition": "Fou"
                },
                {
                    "name": "Stables",
                    "definition": "Écuries"
                },
                {
                    "name": "Peg",
                    "definition": "Cheville / Piquet"
                },
                {
                    "name": "Pens",
                    "definition": "Enclos / Stylos"
                },
                {
                    "name": "Slate",
                    "definition": "Ardoise"
                },
                {
                    "name": "Colliery",
                    "definition": "Mine de charbon"
                },
                {
                    "name": "Drams",
                    "definition": "Gorgées"
                },
                {
                    "name": "Seam",
                    "definition": "Filon / Coutures"
                },
                {
                    "name": "Coarse",
                    "definition": "Grossier"
                },
                {
                    "name": "Padded",
                    "definition": "Rembourré"
                },
                {
                    "name": "Loomed",
                    "definition": "Se profilait"
                },
                {
                    "name": "Spire",
                    "definition": "Flèche (d’église)"
                },
                {
                    "name": "Clerk",
                    "definition": "Employé / Clerc"
                },
                {
                    "name": "Collar",
                    "definition": "Col"
                },
                {
                    "name": "Cuffs",
                    "definition": "Poignets"
                },
                {
                    "name": "Timber",
                    "definition": "Bois"
                },
                {
                    "name": "Ledger",
                    "definition": "Grand livre comptable"
                },
                {
                    "name": "Bowler",
                    "definition": "Chapeau melon"
                },
                {
                    "name": "Badge",
                    "definition": "Insigne"
                },
                {
                    "name": "Stubble",
                    "definition": "Barbe naissante"
                },
                {
                    "name": "Chairman",
                    "definition": "Président"
                },
                {
                    "name": "Tailcoat",
                    "definition": "Queue-de-pie"
                },
                {
                    "name": "Stirring",
                    "definition": "Émouvant"
                },
                {
                    "name": "Cheek",
                    "definition": "Culot"
                },
                {
                    "name": "Sniggered",
                    "definition": "Ricana"
                },
                {
                    "name": "Set his cap at someone",
                    "definition": "Courtiser quelqu’un"
                },
                {
                    "name": "Yardstick",
                    "definition": "Mètre"
                }
            ]
        }
    ]
}